pseudorust/__init__.py
pseudorust/dunder_functions.py
pseudorust/info.py
pseudorust/protocols.py
pseudorust/py.typed
pseudorust/tagged_variants/__init__.py
pseudorust/tagged_variants/_err.py
pseudorust/tagged_variants/_null.py
pseudorust/tagged_variants/_ok.py
pseudorust/tagged_variants/_variant.py
pseudorust/tagged_variants/optional.py
pseudorust/tagged_variants/panics.py
pseudorust/tagged_variants/result.py
pseudorust-0.1.0.dist-info/LICENSE
pseudorust-0.1.0.dist-info/METADATA
pseudorust-0.1.0.dist-info/WHEEL
pseudorust-0.1.0.dist-info/top_level.txt
pseudorust-0.1.0.dist-info/RECORD
