Metadata-Version: 2.1
Name: pseudorust
Version: 0.1.0
Summary: All the types I don't want to implement twice.
Author-email: Ernest Izdebski <44341687+ernieIzde8ski@users.noreply.github.com>
License: Copyright 2024-present Ernest Izdebski
Project-URL: Homepage, https://github.com/ernieIzde8ski/pseudorust
Project-URL: Issues, https://github.com/ernieIzde8ski/pseudorust/issues
Classifier: Programming Language :: Python :: 3
Classifier: License :: OSI Approved :: MIT License
Classifier: Operating System :: OS Independent
Requires-Python: >=3.10
License-File: LICENSE
Requires-Dist: typing-extensions >=4.12.2
